setup.py
parrot/__init__.py
parrot/parrot.py
python_parrot.egg-info/PKG-INFO
python_parrot.egg-info/SOURCES.txt
python_parrot.egg-info/dependency_links.txt
python_parrot.egg-info/entry_points.txt
python_parrot.egg-info/requires.txt
python_parrot.egg-info/top_level.txt