Metadata-Version: 1.1
Name: python-parrot
Version: 1.0.1
Summary: Parrot is a simple HTTP server that responds to requests with a specified filename
Home-page: https://github.com/sjkingo/python-parrot
Author: Sam Kingston
Author-email: sam@sjkwi.com.au
License: BSD
Platform: UNKNOWN
Classifier: Intended Audience :: Developers
Classifier: License :: OSI Approved :: BSD License
Classifier: Programming Language :: Python
Classifier: Programming Language :: Python :: 3
Classifier: Programming Language :: Python :: 3.4
